lwdp/__init__.py
lwdp/cache.py
lwdp/stage.py
lwdp-0.0.5.dist-info/LICENSE
lwdp-0.0.5.dist-info/METADATA
lwdp-0.0.5.dist-info/WHEEL
lwdp-0.0.5.dist-info/top_level.txt
lwdp-0.0.5.dist-info/RECORD
