Metadata-Version: 2.1
Name: lwdp
Version: 0.0.5
Summary: Lightweight Data Pipeline for with code-based stage cacheing
Author-email: Nick Padon <npadon@gmail.com>
License: MIT License        
Project-URL: Homepage, https://github.com/npadon/lwdp
Project-URL: Bug Tracker, https://github.com/npadon/lwdp/issues
Classifier: Programming Language :: Python :: 3
Classifier: License :: OSI Approved :: MIT License
Classifier: Operating System :: OS Independent
Requires-Python: >=3.9
License-File: LICENSE
Requires-Dist: pandas
